rich_tea/__init__.py
rich_tea/__main__.py
rich_tea/events.py
rich_tea/list_select.py
rich_tea/py.typed
rich_tea/text_box.py
rich_tea/util.py
rich_tea-0.3.0.dist-info/WHEEL
rich_tea-0.3.0.dist-info/METADATA
rich_tea-0.3.0.dist-info/RECORD
