Metadata-Version: 2.1
Name: rich-tea
Version: 0.3.0
Summary: Tools for approximating The Elm Architecture, powered by Rich
Home-page: https://github.com/aatifsyed/rich-tea
License: MIT
Author: Aatif Syed
Author-email: aatifsyedyp@gmail.com
Requires-Python: >=3.8,<4.0
Classifier: License :: OSI Approved :: MIT License
Classifier: Programming Language :: Python :: 3
Classifier: Programming Language :: Python :: 3.10
Classifier: Programming Language :: Python :: 3.8
Classifier: Programming Language :: Python :: 3.9
Requires-Dist: more-itertools (>=8.12.0,<9.0.0)
Requires-Dist: prompt-toolkit (>=3.0.24,<4.0.0)
Requires-Dist: returns (>=0.18.0,<0.19.0)
Requires-Dist: rich (>=11.0.0,<12.0.0)
Project-URL: Repository, https://github.com/aatifsyed/rich-tea
